httpmq/__init__.py
httpmq/client.py
httpmq/common.py
httpmq/dataplane.py
httpmq/management.py
httpmq/models/__init__.py
httpmq/models/apis_api_rest_req_stream_subjects.py
httpmq/models/apis_api_rest_resp_all_jet_stream_consumers.py
httpmq/models/apis_api_rest_resp_all_jet_streams.py
httpmq/models/apis_api_rest_resp_consumer_config.py
httpmq/models/apis_api_rest_resp_consumer_info.py
httpmq/models/apis_api_rest_resp_data_message.py
httpmq/models/apis_api_rest_resp_one_jet_stream.py
httpmq/models/apis_api_rest_resp_one_jet_stream_consumer.py
httpmq/models/apis_api_rest_resp_sequence_info.py
httpmq/models/apis_api_rest_resp_stream_config.py
httpmq/models/apis_api_rest_resp_stream_info.py
httpmq/models/apis_api_rest_resp_stream_state.py
httpmq/models/base_model_.py
httpmq/models/dataplane_ack_seq_num.py
httpmq/models/dataplane_msg_to_deliver_seq.py
httpmq/models/goutils_error_detail.py
httpmq/models/goutils_rest_api_base_response.py
httpmq/models/management_jet_stream_consumer_param.py
httpmq/models/management_js_stream_limits.py
httpmq/models/management_js_stream_param.py
httpmq/typing_utils.py
httpmq/util.py
httpmq-0.1.0.dist-info/LICENSE
httpmq-0.1.0.dist-info/WHEEL
httpmq-0.1.0.dist-info/METADATA
httpmq-0.1.0.dist-info/RECORD
