Metadata-Version: 2.1
Name: httpmq
Version: 0.1.0
Summary: HTTP MQ Python client module
Home-page: https://github.com/alwitt/httpmq-python
License: MIT
Keywords: httpmq
Author: Rhine Cliff
Author-email: rhinecliff@protonmail.com
Requires-Python: >=3.7.2,<4.0
Classifier: License :: OSI Approved :: MIT License
Classifier: Operating System :: OS Independent
Classifier: Programming Language :: Python :: 3
Classifier: Programming Language :: Python :: 3.10
Classifier: Programming Language :: Python :: 3.8
Classifier: Programming Language :: Python :: 3.9
Requires-Dist: aiohttp (>=3.8)
Requires-Dist: asyncio (>=3.4)
Requires-Dist: python-dateutil (>=2.8)
Project-URL: Bug Tracker, https://github.com/alwitt/httpmq-python/issues
Project-URL: Repository, https://github.com/alwitt/httpmq-python
